bambu_cli-0.5.10.dist-info/METADATA
bambu_cli-0.5.10.dist-info/WHEEL
bambu_cli-0.5.10.dist-info/entry_points.txt
bambu_cli-0.5.10.dist-info/licenses/LICENSE
bambucli/__init__.py
bambucli/actions/__init__.py
bambucli/actions/addcloud.py
bambucli/actions/addlocal.py
bambucli/actions/enablengrok.py
bambucli/actions/ensureaccount.py
bambucli/actions/ensureip.py
bambucli/actions/info.py
bambucli/actions/listfiles.py
bambucli/actions/login.py
bambucli/actions/monitor.py
bambucli/actions/print.py
bambucli/actions/project.py
bambucli/actions/read3mf.py
bambucli/actions/upload.py
bambucli/bambu/account.py
bambucli/bambu/ftpclient.py
bambucli/bambu/httpapi.py
bambucli/bambu/messages/getversion.py
bambucli/bambu/messages/onpushstatus.py
bambucli/bambu/mqttclient.py
bambucli/bambu/printer.py
bambucli/bambu/printstages.py
bambucli/bambu/project.py
bambucli/bambu/projectfilereader.py
bambucli/bambu/speedprofiles.py
bambucli/bambu/ssdpclient.py
bambucli/cli.py
bambucli/config.py
bambucli/dashboard.py
bambucli/fileserver.py
bambucli/ftpsimplicit.py
bambucli/printermonitor.py
bambucli/signalingtcpserver.py
bambucli/spinner.py
bambucli/strfdelta.py
bambucli/version.py
bambu_cli-0.5.10.dist-info/RECORD
