Metadata-Version: 2.1
Name: bambu-cli
Version: 0.5.10
Summary: CLI tool for use with Bambu Printers
Author-Email: Andrew Todd <thegeektechworkshop@gmail.com>
License: GPL3
Requires-Python: ~=3.12
Requires-Dist: paho-mqtt>=2.1.0
Requires-Dist: ftputil>=5.1.0
Requires-Dist: enlighten>=1.12.4
Requires-Dist: sshkeyboard>=2.3.1
Requires-Dist: rich>=13.9.4
Requires-Dist: cloudscraper>=1.2.71
Requires-Dist: certifi>=2024.8.30
Requires-Dist: ngrok>=1.4.0
Requires-Dist: ssdp>=1.3.0
Requires-Dist: untangle>=1.2.1
Requires-Dist: ipaddress>=1.0.23
